codechembook/__init__.py
codechembook/numericalTools.py
codechembook/plotlyTemplates.py
codechembook/quickPlots.py
codechembook/quickTools.py
codechembook/symbols/__init__.py
codechembook/symbols/chem.py
codechembook/symbols/chemformula.py
codechembook/symbols/elements.py
codechembook/symbols/greek.py
codechembook/symbols/math.py
codechembook/symbols/script.py
codechembook/symbols/typesettingHTML.py
codechembook/symbols/typography.py
codechembook/writingTools/linbylineformatter.py
codechembook-1.3.0.dist-info/licenses/LICENSE
codechembook-1.3.0.dist-info/METADATA
codechembook-1.3.0.dist-info/WHEEL
codechembook-1.3.0.dist-info/top_level.txt
codechembook-1.3.0.dist-info/RECORD
