Metadata-Version: 2.4
Name: codechembook
Version: 1.3.0
Summary: Companion package to 'Coding for Chemists' containing helpful functions for common tasks.
License: MIT License
Project-URL: Homepage, https://www.codechembook.com
Keywords: chemistry,plotting,plotly,histogram
Classifier: License :: OSI Approved :: MIT License
Classifier: Programming Language :: Python
Classifier: Programming Language :: Python :: 3
Requires-Python: >=3.11
License-File: LICENSE
Requires-Dist: kaleido>=0.1.0
Requires-Dist: plotly
Requires-Dist: lmfit
Requires-Dist: numpy
Requires-Dist: scipy
Dynamic: license-file
